CFA.py
CFAV1.py
Factory.py
IDA.py
IDAV1.py
Superfluid.py
Supertoken.py
account_provider.py
con_addresses.py
host.py
provider.py
superfluid.py
supertoken.py
supertoken_factory.py
token_addresses.py
superfluid_finance-0.0.5.dist-info/LICENSE.txt
superfluid_finance-0.0.5.dist-info/METADATA
superfluid_finance-0.0.5.dist-info/WHEEL
superfluid_finance-0.0.5.dist-info/top_level.txt
superfluid_finance-0.0.5.dist-info/RECORD
