Metadata-Version: 2.1
Name: superfluid-finance
Version: 0.0.5
Summary: A python package for interacting with the superfluid-finance primitive in your application
Home-page: https://github.com/phydy/superfluidpy
Author: Phidel Musungu
Author-email: mphidel@gmail.com
Maintainer: Phidel Musungu
Maintainer-email: mphidel@gmail.com
License: UNKNOWN
Platform: UNKNOWN
Classifier: Programming Language :: Python :: 3
Classifier: Programming Language :: Python :: 3.6
Classifier: Programming Language :: Python :: 3.7
Classifier: Programming Language :: Python :: 3.8
Classifier: Programming Language :: Python :: 3.9
Classifier: License :: OSI Approved :: MIT License
Classifier: Development Status :: 4 - Beta
Classifier: Operating System :: OS Independent
Requires-Dist: eth-brownie
Requires-Dist: web3
Provides-Extra: dev
Requires-Dist: pytest (>=3.7) ; extra == 'dev'
Requires-Dist: python (>=3) ; extra == 'dev'
